qtm/__init__.py
qtm/control.py
qtm/discovery.py
qtm/packet.py
qtm/protocol.py
qtm/qrt.py
qtm/reboot.py
qtm/receiver.py
qtm/data/demo.qtm
qtm-2.1.2.dist-info/LICENSE
qtm-2.1.2.dist-info/METADATA
qtm-2.1.2.dist-info/WHEEL
qtm-2.1.2.dist-info/top_level.txt
qtm-2.1.2.dist-info/zip-safe
qtm-2.1.2.dist-info/RECORD
