Metadata-Version: 2.1
Name: qtm
Version: 2.1.2
Summary: DEPRECATED
Home-page: https://github.com/qualisys/qualisys_python_sdk
Author: Martin Gejke
Author-email: support@qualisys.com
License: MIT
Download-URL: https://github.com/qualisys/qualisys_python_sdk/tarball/2.1.2
Platform: UNKNOWN
Classifier: Operating System :: OS Independent
Classifier: Intended Audience :: Developers
Classifier: License :: OSI Approved :: MIT License
Classifier: Programming Language :: Python
Classifier: Programming Language :: Python :: 3.5
Classifier: Programming Language :: Python :: 3.6
Classifier: Programming Language :: Python :: 3.7
Classifier: Topic :: Scientific/Engineering
Classifier: Topic :: Utilities
Requires-Python: >=3.5.3
